{
  "timestamp": "20250524_231803",
  "moves": [
    {
      "x": 3,
      "y": 7,
      "hit": false,
      "player_type": "player",
      "timestamp": "2025-05-24T23:18:04.107963"
    },
    {
      "x": 5,
      "y": 6,
      "hit": false,
      "player_type": "enemy",
      "timestamp": "2025-05-24T23:18:04.237792"
    },
    {
      "x": 5,
      "y": 8,
      "hit": false,
      "player_type": "player",
      "timestamp": "2025-05-24T23:18:04.374827"
    },
    {
      "x": 3,
      "y": 4,
      "hit": false,
      "player_type": "enemy",
      "timestamp": "2025-05-24T23:18:04.506179"
    },
    {
      "x": 1,
      "y": 2,
      "hit": false,
      "player_type": "player",
      "timestamp": "2025-05-24T23:18:04.640299"
    },
    {
      "x": 9,
      "y": 4,
      "hit": true,
      "player_type": "enemy",
      "timestamp": "2025-05-24T23:18:04.771031"
    },
    {
      "x": 9,
      "y": 5,
      "hit": true,
      "player_type": "enemy",
      "timestamp": "2025-05-24T23:18:04.950709"
    },
    {
      "x": 9,
      "y": 2,
      "hit": false,
      "player_type": "enemy",
      "timestamp": "2025-05-24T23:18:05.130207"
    },
    {
      "x": 0,
      "y": 5,
      "hit": false,
      "player_type": "player",
      "timestamp": "2025-05-24T23:18:05.266154"
    },
    {
      "x": 4,
      "y": 9,
      "hit": false,
      "player_type": "enemy",
      "timestamp": "2025-05-24T23:18:05.395433"
    },
    {
      "x": 4,
      "y": 4,
      "hit": false,
      "player_type": "player",
      "timestamp": "2025-05-24T23:18:05.529446"
    },
    {
      "x": 5,
      "y": 7,
      "hit": true,
      "player_type": "enemy",
      "timestamp": "2025-05-24T23:18:05.660517"
    },
    {
      "x": 4,
      "y": 7,
      "hit": false,
      "player_type": "enemy",
      "timestamp": "2025-05-24T23:18:05.840716"
    },
    {
      "x": 6,
      "y": 1,
      "hit": false,
      "player_type": "player",
      "timestamp": "2025-05-24T23:18:05.979264"
    },
    {
      "x": 6,
      "y": 7,
      "hit": false,
      "player_type": "enemy",
      "timestamp": "2025-05-24T23:18:06.111954"
    },
    {
      "x": 9,
      "y": 6,
      "hit": true,
      "player_type": "player",
      "timestamp": "2025-05-24T23:18:06.246179"
    },
    {
      "x": 6,
      "y": 3,
      "hit": false,
      "player_type": "player",
      "timestamp": "2025-05-24T23:18:06.422076"
    },
    {
      "x": 5,
      "y": 8,
      "hit": true,
      "player_type": "enemy",
      "timestamp": "2025-05-24T23:18:06.551026"
    },
    {
      "x": 2,
      "y": 5,
      "hit": false,
      "player_type": "enemy",
      "timestamp": "2025-05-24T23:18:06.729241"
    },
    {
      "x": 4,
      "y": 2,
      "hit": true,
      "player_type": "player",
      "timestamp": "2025-05-24T23:18:06.862945"
    },
    {
      "x": 4,
      "y": 3,
      "hit": false,
      "player_type": "player",
      "timestamp": "2025-05-24T23:18:07.037319"
    },
    {
      "x": 3,
      "y": 3,
      "hit": false,
      "player_type": "enemy",
      "timestamp": "2025-05-24T23:18:07.164336"
    },
    {
      "x": 5,
      "y": 2,
      "hit": false,
      "player_type": "player",
      "timestamp": "2025-05-24T23:18:07.299669"
    },
    {
      "x": 0,
      "y": 6,
      "hit": true,
      "player_type": "enemy",
      "timestamp": "2025-05-24T23:18:07.428310"
    },
    {
      "x": 1,
      "y": 6,
      "hit": true,
      "player_type": "enemy",
      "timestamp": "2025-05-24T23:18:07.607842"
    },
    {
      "x": 4,
      "y": 1,
      "hit": false,
      "player_type": "enemy",
      "timestamp": "2025-05-24T23:18:07.786958"
    },
    {
      "x": 4,
      "y": 1,
      "hit": true,
      "player_type": "player",
      "timestamp": "2025-05-24T23:18:07.920474"
    },
    {
      "x": 5,
      "y": 1,
      "hit": false,
      "player_type": "player",
      "timestamp": "2025-05-24T23:18:08.094110"
    },
    {
      "x": 1,
      "y": 1,
      "hit": false,
      "player_type": "enemy",
      "timestamp": "2025-05-24T23:18:08.222538"
    },
    {
      "x": 4,
      "y": 0,
      "hit": true,
      "player_type": "player",
      "timestamp": "2025-05-24T23:18:08.358393"
    },
    {
      "x": 6,
      "y": 6,
      "hit": false,
      "player_type": "player",
      "timestamp": "2025-05-24T23:18:08.532877"
    },
    {
      "x": 9,
      "y": 0,
      "hit": true,
      "player_type": "enemy",
      "timestamp": "2025-05-24T23:18:08.660648"
    },
    {
      "x": 3,
      "y": 0,
      "hit": false,
      "player_type": "enemy",
      "timestamp": "2025-05-24T23:18:08.838261"
    },
    {
      "x": 8,
      "y": 0,
      "hit": false,
      "player_type": "player",
      "timestamp": "2025-05-24T23:18:08.975319"
    },
    {
      "x": 2,
      "y": 2,
      "hit": true,
      "player_type": "enemy",
      "timestamp": "2025-05-24T23:18:09.106671"
    },
    {
      "x": 3,
      "y": 2,
      "hit": false,
      "player_type": "enemy",
      "timestamp": "2025-05-24T23:18:09.288870"
    },
    {
      "x": 9,
      "y": 3,
      "hit": false,
      "player_type": "player",
      "timestamp": "2025-05-24T23:18:09.424137"
    },
    {
      "x": 2,
      "y": 1,
      "hit": false,
      "player_type": "enemy",
      "timestamp": "2025-05-24T23:18:09.554824"
    },
    {
      "x": 0,
      "y": 9,
      "hit": true,
      "player_type": "player",
      "timestamp": "2025-05-24T23:18:09.689346"
    },
    {
      "x": 1,
      "y": 9,
      "hit": false,
      "player_type": "player",
      "timestamp": "2025-05-24T23:18:09.865026"
    },
    {
      "x": 1,
      "y": 2,
      "hit": true,
      "player_type": "enemy",
      "timestamp": "2025-05-24T23:18:09.995104"
    },
    {
      "x": 1,
      "y": 3,
      "hit": false,
      "player_type": "enemy",
      "timestamp": "2025-05-24T23:18:10.174016"
    },
    {
      "x": 0,
      "y": 8,
      "hit": true,
      "player_type": "player",
      "timestamp": "2025-05-24T23:18:10.308449"
    },
    {
      "x": 1,
      "y": 8,
      "hit": false,
      "player_type": "player",
      "timestamp": "2025-05-24T23:18:10.484305"
    },
    {
      "x": 0,
      "y": 2,
      "hit": true,
      "player_type": "enemy",
      "timestamp": "2025-05-24T23:18:10.614639"
    },
    {
      "x": 6,
      "y": 4,
      "hit": false,
      "player_type": "enemy",
      "timestamp": "2025-05-24T23:18:10.792557"
    },
    {
      "x": 0,
      "y": 7,
      "hit": true,
      "player_type": "player",
      "timestamp": "2025-05-24T23:18:10.931264"
    },
    {
      "x": 1,
      "y": 7,
      "hit": false,
      "player_type": "player",
      "timestamp": "2025-05-24T23:18:11.105228"
    },
    {
      "x": 5,
      "y": 3,
      "hit": false,
      "player_type": "enemy",
      "timestamp": "2025-05-24T23:18:11.234948"
    },
    {
      "x": 0,
      "y": 6,
      "hit": true,
      "player_type": "player",
      "timestamp": "2025-05-24T23:18:11.372036"
    },
    {
      "x": 3,
      "y": 9,
      "hit": false,
      "player_type": "player",
      "timestamp": "2025-05-24T23:18:11.546458"
    },
    {
      "x": 7,
      "y": 6,
      "hit": true,
      "player_type": "enemy",
      "timestamp": "2025-05-24T23:18:11.677109"
    },
    {
      "x": 7,
      "y": 5,
      "hit": true,
      "player_type": "enemy",
      "timestamp": "2025-05-24T23:18:11.855559"
    },
    {
      "x": 7,
      "y": 4,
      "hit": true,
      "player_type": "enemy",
      "timestamp": "2025-05-24T23:18:12.036051"
    },
    {
      "x": 7,
      "y": 1,
      "hit": false,
      "player_type": "enemy",
      "timestamp": "2025-05-24T23:18:12.215822"
    },
    {
      "x": 1,
      "y": 0,
      "hit": false,
      "player_type": "player",
      "timestamp": "2025-05-24T23:18:12.351700"
    },
    {
      "x": 7,
      "y": 9,
      "hit": false,
      "player_type": "enemy",
      "timestamp": "2025-05-24T23:18:12.482535"
    },
    {
      "x": 7,
      "y": 9,
      "hit": true,
      "player_type": "player",
      "timestamp": "2025-05-24T23:18:12.620016"
    },
    {
      "x": 8,
      "y": 9,
      "hit": false,
      "player_type": "player",
      "timestamp": "2025-05-24T23:18:12.795410"
    },
    {
      "x": 3,
      "y": 9,
      "hit": false,
      "player_type": "enemy",
      "timestamp": "2025-05-24T23:18:12.926368"
    },
    {
      "x": 7,
      "y": 8,
      "hit": true,
      "player_type": "player",
      "timestamp": "2025-05-24T23:18:13.060303"
    },
    {
      "x": 0,
      "y": 0,
      "hit": false,
      "player_type": "player",
      "timestamp": "2025-05-24T23:18:13.233947"
    },
    {
      "x": 5,
      "y": 1,
      "hit": false,
      "player_type": "enemy",
      "timestamp": "2025-05-24T23:18:13.364918"
    },
    {
      "x": 7,
      "y": 3,
      "hit": false,
      "player_type": "player",
      "timestamp": "2025-05-24T23:18:13.499947"
    },
    {
      "x": 3,
      "y": 7,
      "hit": false,
      "player_type": "enemy",
      "timestamp": "2025-05-24T23:18:13.632572"
    },
    {
      "x": 1,
      "y": 3,
      "hit": false,
      "player_type": "player",
      "timestamp": "2025-05-24T23:18:13.769672"
    },
    {
      "x": 5,
      "y": 2,
      "hit": false,
      "player_type": "enemy",
      "timestamp": "2025-05-24T23:18:13.900047"
    },
    {
      "x": 4,
      "y": 5,
      "hit": false,
      "player_type": "player",
      "timestamp": "2025-05-24T23:18:14.034008"
    },
    {
      "x": 9,
      "y": 7,
      "hit": false,
      "player_type": "enemy",
      "timestamp": "2025-05-24T23:18:14.165364"
    },
    {
      "x": 9,
      "y": 0,
      "hit": false,
      "player_type": "player",
      "timestamp": "2025-05-24T23:18:14.300784"
    },
    {
      "x": 8,
      "y": 9,
      "hit": false,
      "player_type": "enemy",
      "timestamp": "2025-05-24T23:18:14.435509"
    },
    {
      "x": 6,
      "y": 5,
      "hit": false,
      "player_type": "player",
      "timestamp": "2025-05-24T23:18:14.576404"
    },
    {
      "x": 0,
      "y": 4,
      "hit": false,
      "player_type": "enemy",
      "timestamp": "2025-05-24T23:18:14.707298"
    },
    {
      "x": 9,
      "y": 2,
      "hit": false,
      "player_type": "player",
      "timestamp": "2025-05-24T23:18:14.843127"
    },
    {
      "x": 5,
      "y": 5,
      "hit": true,
      "player_type": "enemy",
      "timestamp": "2025-05-24T23:18:14.977130"
    },
    {
      "x": 4,
      "y": 0,
      "hit": true,
      "player_type": "enemy",
      "timestamp": "2025-05-24T23:18:15.155344"
    },
    {
      "x": 4,
      "y": 3,
      "hit": false,
      "player_type": "enemy",
      "timestamp": "2025-05-24T23:18:15.335044"
    },
    {
      "x": 3,
      "y": 6,
      "hit": false,
      "player_type": "player",
      "timestamp": "2025-05-24T23:18:15.472945"
    },
    {
      "x": 9,
      "y": 8,
      "hit": true,
      "player_type": "enemy",
      "timestamp": "2025-05-24T23:18:15.604609"
    },
    {
      "x": 2,
      "y": 9,
      "hit": false,
      "player_type": "enemy",
      "timestamp": "2025-05-24T23:18:15.786486"
    },
    {
      "x": 9,
      "y": 9,
      "hit": false,
      "player_type": "player",
      "timestamp": "2025-05-24T23:18:15.921748"
    },
    {
      "x": 3,
      "y": 5,
      "hit": false,
      "player_type": "enemy",
      "timestamp": "2025-05-24T23:18:16.054377"
    },
    {
      "x": 7,
      "y": 1,
      "hit": false,
      "player_type": "player",
      "timestamp": "2025-05-24T23:18:16.188525"
    },
    {
      "x": 4,
      "y": 2,
      "hit": false,
      "player_type": "enemy",
      "timestamp": "2025-05-24T23:18:16.319884"
    },
    {
      "x": 4,
      "y": 9,
      "hit": true,
      "player_type": "player",
      "timestamp": "2025-05-24T23:18:16.457068"
    },
    {
      "x": 5,
      "y": 9,
      "hit": true,
      "player_type": "player",
      "timestamp": "2025-05-24T23:18:16.634049"
    },
    {
      "x": 0,
      "y": 2,
      "hit": true,
      "player_type": "player",
      "timestamp": "2025-05-24T23:18:16.808644"
    },
    {
      "x": 0,
      "y": 3,
      "hit": true,
      "player_type": "player",
      "timestamp": "2025-05-24T23:18:16.981263"
    },
    {
      "x": 0,
      "y": 4,
      "hit": true,
      "player_type": "player",
      "timestamp": "2025-05-24T23:18:17.155462"
    },
    {
      "x": 9,
      "y": 1,
      "hit": false,
      "player_type": "player",
      "timestamp": "2025-05-24T23:18:17.330587"
    },
    {
      "x": 0,
      "y": 8,
      "hit": true,
      "player_type": "enemy",
      "timestamp": "2025-05-24T23:18:17.462457"
    },
    {
      "x": 0,
      "y": 9,
      "hit": false,
      "player_type": "enemy",
      "timestamp": "2025-05-24T23:18:17.641696"
    },
    {
      "x": 9,
      "y": 4,
      "hit": false,
      "player_type": "player",
      "timestamp": "2025-05-24T23:18:17.777282"
    },
    {
      "x": 1,
      "y": 8,
      "hit": true,
      "player_type": "enemy",
      "timestamp": "2025-05-24T23:18:17.906673"
    },
    {
      "x": 1,
      "y": 9,
      "hit": false,
      "player_type": "enemy",
      "timestamp": "2025-05-24T23:18:18.086667"
    },
    {
      "x": 4,
      "y": 6,
      "hit": false,
      "player_type": "player",
      "timestamp": "2025-05-24T23:18:18.222818"
    },
    {
      "x": 2,
      "y": 8,
      "hit": true,
      "player_type": "enemy",
      "timestamp": "2025-05-24T23:18:18.354418"
    },
    {
      "x": 3,
      "y": 8,
      "hit": true,
      "player_type": "enemy",
      "timestamp": "2025-05-24T23:18:18.532733"
    }
  ],
  "initial_board_player": [
    [
      0,
      0,
      0,
      0,
      1,
      0,
      0,
      0,
      0,
      1
    ],
    [
      0,
      0,
      0,
      0,
      0,
      0,
      0,
      0,
      0,
      0
    ],
    [
      1,
      1,
      1,
      0,
      0,
      0,
      0,
      0,
      0,
      0
    ],
    [
      0,
      0,
      0,
      0,
      0,
      0,
      0,
      0,
      0,
      0
    ],
    [
      0,
      0,
      0,
      0,
      0,
      0,
      0,
      1,
      0,
      1
    ],
    [
      0,
      0,
      0,
      0,
      0,
      1,
      0,
      1,
      0,
      1
    ],
    [
      1,
      1,
      0,
      0,
      0,
      0,
      0,
      1,
      0,
      0
    ],
    [
      0,
      0,
      0,
      0,
      0,
      1,
      0,
      0,
      0,
      0
    ],
    [
      1,
      1,
      1,
      1,
      0,
      1,
      0,
      0,
      0,
      1
    ],
    [
      0,
      0,
      0,
      0,
      0,
      0,
      0,
      0,
      0,
      0
    ]
  ],
  "initial_board_ai": [
    [
      0,
      0,
      0,
      0,
      1,
      0,
      0,
      0,
      0,
      0
    ],
    [
      0,
      0,
      1,
      0,
      1,
      0,
      0,
      0,
      1,
      0
    ],
    [
      1,
      0,
      0,
      0,
      1,
      0,
      0,
      0,
      1,
      0
    ],
    [
      1,
      0,
      0,
      0,
      0,
      0,
      0,
      0,
      0,
      0
    ],
    [
      1,
      0,
      0,
      0,
      0,
      0,
      0,
      0,
      0,
      0
    ],
    [
      0,
      0,
      0,
      0,
      0,
      0,
      0,
      0,
      0,
      0
    ],
    [
      1,
      0,
      0,
      0,
      0,
      0,
      0,
      0,
      0,
      1
    ],
    [
      1,
      0,
      1,
      0,
      0,
      0,
      0,
      0,
      0,
      0
    ],
    [
      1,
      0,
      0,
      0,
      0,
      0,
      0,
      1,
      0,
      1
    ],
    [
      1,
      0,
      0,
      0,
      1,
      1,
      0,
      1,
      0,
      0
    ]
  ],
  "winner": "enemy",
  "total_moves": 98,
  "hits": 35,
  "misses": 63,
  "player_type": "ai",
  "player_ai_type": "algorithmic",
  "enemy_ai_type": "transformer",
  "player_board": null,
  "enemy_board": null,
  "start_time": null,
  "end_time": "2025-05-24T23:18:18.550880"
}