{
  "timestamp": "20250524_230540",
  "moves": [
    {
      "x": 0,
      "y": 3,
      "hit": true,
      "player_type": "enemy",
      "timestamp": "2025-05-24T23:05:41.069365"
    },
    {
      "x": 0,
      "y": 2,
      "hit": false,
      "player_type": "enemy",
      "timestamp": "2025-05-24T23:05:41.246039"
    },
    {
      "x": 8,
      "y": 5,
      "hit": false,
      "player_type": "player",
      "timestamp": "2025-05-24T23:05:41.379508"
    },
    {
      "x": 0,
      "y": 4,
      "hit": false,
      "player_type": "enemy",
      "timestamp": "2025-05-24T23:05:41.513038"
    },
    {
      "x": 2,
      "y": 7,
      "hit": false,
      "player_type": "player",
      "timestamp": "2025-05-24T23:05:41.641494"
    },
    {
      "x": 1,
      "y": 3,
      "hit": true,
      "player_type": "enemy",
      "timestamp": "2025-05-24T23:05:41.769338"
    },
    {
      "x": 2,
      "y": 7,
      "hit": true,
      "player_type": "enemy",
      "timestamp": "2025-05-24T23:05:41.950532"
    },
    {
      "x": 3,
      "y": 7,
      "hit": false,
      "player_type": "enemy",
      "timestamp": "2025-05-24T23:05:42.127235"
    },
    {
      "x": 8,
      "y": 2,
      "hit": false,
      "player_type": "player",
      "timestamp": "2025-05-24T23:05:42.256884"
    },
    {
      "x": 2,
      "y": 8,
      "hit": false,
      "player_type": "enemy",
      "timestamp": "2025-05-24T23:05:42.385280"
    },
    {
      "x": 1,
      "y": 9,
      "hit": false,
      "player_type": "player",
      "timestamp": "2025-05-24T23:05:42.518256"
    },
    {
      "x": 1,
      "y": 7,
      "hit": true,
      "player_type": "enemy",
      "timestamp": "2025-05-24T23:05:42.650807"
    },
    {
      "x": 0,
      "y": 7,
      "hit": true,
      "player_type": "enemy",
      "timestamp": "2025-05-24T23:05:42.833199"
    },
    {
      "x": 6,
      "y": 0,
      "hit": true,
      "player_type": "enemy",
      "timestamp": "2025-05-24T23:05:43.011581"
    },
    {
      "x": 5,
      "y": 0,
      "hit": false,
      "player_type": "enemy",
      "timestamp": "2025-05-24T23:05:43.188844"
    },
    {
      "x": 3,
      "y": 1,
      "hit": false,
      "player_type": "player",
      "timestamp": "2025-05-24T23:05:43.316552"
    },
    {
      "x": 7,
      "y": 0,
      "hit": false,
      "player_type": "enemy",
      "timestamp": "2025-05-24T23:05:43.449770"
    },
    {
      "x": 5,
      "y": 3,
      "hit": false,
      "player_type": "player",
      "timestamp": "2025-05-24T23:05:43.585250"
    },
    {
      "x": 6,
      "y": 1,
      "hit": true,
      "player_type": "enemy",
      "timestamp": "2025-05-24T23:05:43.717088"
    },
    {
      "x": 9,
      "y": 4,
      "hit": true,
      "player_type": "enemy",
      "timestamp": "2025-05-24T23:05:43.896289"
    },
    {
      "x": 9,
      "y": 5,
      "hit": true,
      "player_type": "enemy",
      "timestamp": "2025-05-24T23:05:44.073328"
    },
    {
      "x": 9,
      "y": 6,
      "hit": true,
      "player_type": "enemy",
      "timestamp": "2025-05-24T23:05:44.250741"
    },
    {
      "x": 7,
      "y": 7,
      "hit": false,
      "player_type": "enemy",
      "timestamp": "2025-05-24T23:05:44.429986"
    },
    {
      "x": 0,
      "y": 1,
      "hit": true,
      "player_type": "player",
      "timestamp": "2025-05-24T23:05:44.558262"
    },
    {
      "x": 8,
      "y": 9,
      "hit": false,
      "player_type": "player",
      "timestamp": "2025-05-24T23:05:44.732683"
    },
    {
      "x": 4,
      "y": 7,
      "hit": true,
      "player_type": "enemy",
      "timestamp": "2025-05-24T23:05:44.862523"
    },
    {
      "x": 4,
      "y": 6,
      "hit": true,
      "player_type": "enemy",
      "timestamp": "2025-05-24T23:05:45.040683"
    },
    {
      "x": 4,
      "y": 5,
      "hit": true,
      "player_type": "enemy",
      "timestamp": "2025-05-24T23:05:45.219434"
    },
    {
      "x": 4,
      "y": 4,
      "hit": true,
      "player_type": "enemy",
      "timestamp": "2025-05-24T23:05:45.397262"
    },
    {
      "x": 5,
      "y": 9,
      "hit": false,
      "player_type": "enemy",
      "timestamp": "2025-05-24T23:05:45.572603"
    },
    {
      "x": 0,
      "y": 4,
      "hit": false,
      "player_type": "player",
      "timestamp": "2025-05-24T23:05:45.703037"
    },
    {
      "x": 4,
      "y": 2,
      "hit": false,
      "player_type": "enemy",
      "timestamp": "2025-05-24T23:05:45.836399"
    },
    {
      "x": 4,
      "y": 6,
      "hit": false,
      "player_type": "player",
      "timestamp": "2025-05-24T23:05:45.969096"
    },
    {
      "x": 4,
      "y": 9,
      "hit": false,
      "player_type": "enemy",
      "timestamp": "2025-05-24T23:05:46.103504"
    },
    {
      "x": 6,
      "y": 0,
      "hit": false,
      "player_type": "player",
      "timestamp": "2025-05-24T23:05:46.240067"
    },
    {
      "x": 7,
      "y": 6,
      "hit": false,
      "player_type": "enemy",
      "timestamp": "2025-05-24T23:05:46.371272"
    },
    {
      "x": 5,
      "y": 9,
      "hit": false,
      "player_type": "player",
      "timestamp": "2025-05-24T23:05:46.502756"
    },
    {
      "x": 6,
      "y": 9,
      "hit": true,
      "player_type": "enemy",
      "timestamp": "2025-05-24T23:05:46.639854"
    },
    {
      "x": 6,
      "y": 4,
      "hit": false,
      "player_type": "enemy",
      "timestamp": "2025-05-24T23:05:46.818482"
    },
    {
      "x": 8,
      "y": 0,
      "hit": false,
      "player_type": "player",
      "timestamp": "2025-05-24T23:05:46.946773"
    },
    {
      "x": 2,
      "y": 9,
      "hit": false,
      "player_type": "enemy",
      "timestamp": "2025-05-24T23:05:47.081782"
    },
    {
      "x": 8,
      "y": 7,
      "hit": false,
      "player_type": "player",
      "timestamp": "2025-05-24T23:05:47.218859"
    },
    {
      "x": 0,
      "y": 9,
      "hit": false,
      "player_type": "enemy",
      "timestamp": "2025-05-24T23:05:47.352456"
    },
    {
      "x": 6,
      "y": 7,
      "hit": false,
      "player_type": "player",
      "timestamp": "2025-05-24T23:05:47.486401"
    },
    {
      "x": 1,
      "y": 9,
      "hit": false,
      "player_type": "enemy",
      "timestamp": "2025-05-24T23:05:47.620241"
    },
    {
      "x": 6,
      "y": 5,
      "hit": false,
      "player_type": "player",
      "timestamp": "2025-05-24T23:05:47.754110"
    },
    {
      "x": 3,
      "y": 9,
      "hit": false,
      "player_type": "enemy",
      "timestamp": "2025-05-24T23:05:47.884724"
    },
    {
      "x": 3,
      "y": 9,
      "hit": false,
      "player_type": "player",
      "timestamp": "2025-05-24T23:05:48.019631"
    },
    {
      "x": 0,
      "y": 5,
      "hit": false,
      "player_type": "enemy",
      "timestamp": "2025-05-24T23:05:48.154777"
    },
    {
      "x": 0,
      "y": 6,
      "hit": false,
      "player_type": "player",
      "timestamp": "2025-05-24T23:05:48.289579"
    },
    {
      "x": 4,
      "y": 0,
      "hit": false,
      "player_type": "enemy",
      "timestamp": "2025-05-24T23:05:48.418912"
    },
    {
      "x": 3,
      "y": 3,
      "hit": true,
      "player_type": "player",
      "timestamp": "2025-05-24T23:05:48.549290"
    },
    {
      "x": 3,
      "y": 4,
      "hit": false,
      "player_type": "player",
      "timestamp": "2025-05-24T23:05:48.728021"
    },
    {
      "x": 6,
      "y": 5,
      "hit": false,
      "player_type": "enemy",
      "timestamp": "2025-05-24T23:05:48.857472"
    },
    {
      "x": 4,
      "y": 3,
      "hit": false,
      "player_type": "player",
      "timestamp": "2025-05-24T23:05:48.989032"
    },
    {
      "x": 1,
      "y": 5,
      "hit": false,
      "player_type": "enemy",
      "timestamp": "2025-05-24T23:05:49.119322"
    },
    {
      "x": 3,
      "y": 2,
      "hit": false,
      "player_type": "player",
      "timestamp": "2025-05-24T23:05:49.251476"
    },
    {
      "x": 7,
      "y": 5,
      "hit": false,
      "player_type": "enemy",
      "timestamp": "2025-05-24T23:05:49.385467"
    },
    {
      "x": 2,
      "y": 3,
      "hit": true,
      "player_type": "player",
      "timestamp": "2025-05-24T23:05:49.520698"
    },
    {
      "x": 2,
      "y": 4,
      "hit": false,
      "player_type": "player",
      "timestamp": "2025-05-24T23:05:49.697149"
    },
    {
      "x": 8,
      "y": 0,
      "hit": true,
      "player_type": "enemy",
      "timestamp": "2025-05-24T23:05:49.825167"
    },
    {
      "x": 8,
      "y": 1,
      "hit": true,
      "player_type": "enemy",
      "timestamp": "2025-05-24T23:05:50.004567"
    },
    {
      "x": 0,
      "y": 0,
      "hit": false,
      "player_type": "enemy",
      "timestamp": "2025-05-24T23:05:50.182642"
    },
    {
      "x": 2,
      "y": 2,
      "hit": false,
      "player_type": "player",
      "timestamp": "2025-05-24T23:05:50.313640"
    },
    {
      "x": 6,
      "y": 3,
      "hit": false,
      "player_type": "enemy",
      "timestamp": "2025-05-24T23:05:50.446995"
    },
    {
      "x": 1,
      "y": 3,
      "hit": true,
      "player_type": "player",
      "timestamp": "2025-05-24T23:05:50.581367"
    },
    {
      "x": 9,
      "y": 4,
      "hit": true,
      "player_type": "player",
      "timestamp": "2025-05-24T23:05:50.759972"
    },
    {
      "x": 9,
      "y": 0,
      "hit": false,
      "player_type": "player",
      "timestamp": "2025-05-24T23:05:50.933513"
    },
    {
      "x": 7,
      "y": 4,
      "hit": false,
      "player_type": "enemy",
      "timestamp": "2025-05-24T23:05:51.063886"
    },
    {
      "x": 5,
      "y": 0,
      "hit": false,
      "player_type": "player",
      "timestamp": "2025-05-24T23:05:51.195301"
    },
    {
      "x": 2,
      "y": 1,
      "hit": false,
      "player_type": "enemy",
      "timestamp": "2025-05-24T23:05:51.328970"
    },
    {
      "x": 6,
      "y": 3,
      "hit": false,
      "player_type": "player",
      "timestamp": "2025-05-24T23:05:51.459065"
    },
    {
      "x": 9,
      "y": 8,
      "hit": false,
      "player_type": "enemy",
      "timestamp": "2025-05-24T23:05:51.586524"
    },
    {
      "x": 4,
      "y": 7,
      "hit": false,
      "player_type": "player",
      "timestamp": "2025-05-24T23:05:51.721475"
    },
    {
      "x": 3,
      "y": 2,
      "hit": false,
      "player_type": "enemy",
      "timestamp": "2025-05-24T23:05:51.852062"
    },
    {
      "x": 0,
      "y": 9,
      "hit": false,
      "player_type": "player",
      "timestamp": "2025-05-24T23:05:51.987182"
    },
    {
      "x": 6,
      "y": 7,
      "hit": false,
      "player_type": "enemy",
      "timestamp": "2025-05-24T23:05:52.117773"
    },
    {
      "x": 3,
      "y": 0,
      "hit": true,
      "player_type": "player",
      "timestamp": "2025-05-24T23:05:52.253654"
    },
    {
      "x": 4,
      "y": 0,
      "hit": true,
      "player_type": "player",
      "timestamp": "2025-05-24T23:05:52.431836"
    },
    {
      "x": 2,
      "y": 0,
      "hit": true,
      "player_type": "player",
      "timestamp": "2025-05-24T23:05:52.605129"
    },
    {
      "x": 7,
      "y": 9,
      "hit": false,
      "player_type": "player",
      "timestamp": "2025-05-24T23:05:52.778726"
    },
    {
      "x": 1,
      "y": 0,
      "hit": false,
      "player_type": "enemy",
      "timestamp": "2025-05-24T23:05:52.907580"
    },
    {
      "x": 9,
      "y": 9,
      "hit": false,
      "player_type": "player",
      "timestamp": "2025-05-24T23:05:53.039040"
    },
    {
      "x": 2,
      "y": 0,
      "hit": true,
      "player_type": "enemy",
      "timestamp": "2025-05-24T23:05:53.169007"
    },
    {
      "x": 8,
      "y": 9,
      "hit": false,
      "player_type": "enemy",
      "timestamp": "2025-05-24T23:05:53.353666"
    },
    {
      "x": 9,
      "y": 7,
      "hit": false,
      "player_type": "player",
      "timestamp": "2025-05-24T23:05:53.482891"
    },
    {
      "x": 9,
      "y": 9,
      "hit": true,
      "player_type": "enemy",
      "timestamp": "2025-05-24T23:05:53.618319"
    },
    {
      "x": 2,
      "y": 5,
      "hit": false,
      "player_type": "enemy",
      "timestamp": "2025-05-24T23:05:53.801170"
    },
    {
      "x": 2,
      "y": 6,
      "hit": true,
      "player_type": "player",
      "timestamp": "2025-05-24T23:05:53.931468"
    },
    {
      "x": 3,
      "y": 6,
      "hit": false,
      "player_type": "player",
      "timestamp": "2025-05-24T23:05:54.111188"
    },
    {
      "x": 0,
      "y": 1,
      "hit": false,
      "player_type": "enemy",
      "timestamp": "2025-05-24T23:05:54.240786"
    },
    {
      "x": 2,
      "y": 5,
      "hit": true,
      "player_type": "player",
      "timestamp": "2025-05-24T23:05:54.371881"
    },
    {
      "x": 6,
      "y": 9,
      "hit": false,
      "player_type": "player",
      "timestamp": "2025-05-24T23:05:54.546229"
    },
    {
      "x": 4,
      "y": 1,
      "hit": false,
      "player_type": "enemy",
      "timestamp": "2025-05-24T23:05:54.675110"
    },
    {
      "x": 2,
      "y": 9,
      "hit": false,
      "player_type": "player",
      "timestamp": "2025-05-24T23:05:54.807363"
    },
    {
      "x": 6,
      "y": 6,
      "hit": true,
      "player_type": "enemy",
      "timestamp": "2025-05-24T23:05:54.937622"
    }
  ],
  "initial_board_player": [
    [
      0,
      0,
      1,
      0,
      0,
      0,
      1,
      0,
      1,
      0
    ],
    [
      0,
      0,
      0,
      0,
      0,
      0,
      1,
      0,
      1,
      0
    ],
    [
      0,
      0,
      0,
      0,
      0,
      0,
      0,
      0,
      0,
      0
    ],
    [
      1,
      1,
      0,
      0,
      0,
      0,
      0,
      0,
      0,
      0
    ],
    [
      0,
      0,
      0,
      0,
      1,
      0,
      0,
      0,
      0,
      1
    ],
    [
      0,
      0,
      0,
      0,
      1,
      0,
      0,
      0,
      0,
      1
    ],
    [
      0,
      0,
      0,
      0,
      1,
      0,
      1,
      0,
      0,
      1
    ],
    [
      1,
      1,
      1,
      0,
      1,
      0,
      0,
      0,
      0,
      0
    ],
    [
      0,
      0,
      0,
      0,
      0,
      0,
      0,
      0,
      0,
      0
    ],
    [
      0,
      0,
      0,
      0,
      0,
      0,
      1,
      0,
      0,
      1
    ]
  ],
  "initial_board_ai": [
    [
      0,
      0,
      1,
      1,
      1,
      0,
      0,
      0,
      0,
      0
    ],
    [
      1,
      0,
      0,
      0,
      0,
      0,
      0,
      0,
      0,
      0
    ],
    [
      0,
      0,
      0,
      0,
      0,
      0,
      0,
      0,
      0,
      1
    ],
    [
      0,
      1,
      1,
      1,
      0,
      0,
      0,
      0,
      0,
      0
    ],
    [
      0,
      0,
      0,
      0,
      0,
      1,
      1,
      0,
      0,
      1
    ],
    [
      0,
      0,
      1,
      0,
      0,
      0,
      0,
      0,
      0,
      0
    ],
    [
      0,
      0,
      1,
      0,
      0,
      1,
      1,
      1,
      1,
      0
    ],
    [
      0,
      0,
      0,
      0,
      0,
      0,
      0,
      0,
      0,
      0
    ],
    [
      0,
      0,
      1,
      1,
      0,
      0,
      0,
      1,
      0,
      0
    ],
    [
      0,
      0,
      0,
      0,
      0,
      0,
      0,
      0,
      0,
      0
    ]
  ],
  "winner": "enemy",
  "total_moves": 96,
  "hits": 30,
  "misses": 66,
  "player_type": "ai",
  "player_ai_type": "algorithmic",
  "enemy_ai_type": "transformer",
  "player_board": null,
  "enemy_board": null,
  "start_time": null,
  "end_time": "2025-05-24T23:05:54.958646"
}