{
  "timestamp": "20250524_225144",
  "moves": [
    {
      "x": 2,
      "y": 1,
      "hit": true,
      "player_type": "enemy",
      "timestamp": "2025-05-24T22:51:44.956712"
    },
    {
      "x": 2,
      "y": 0,
      "hit": false,
      "player_type": "enemy",
      "timestamp": "2025-05-24T22:51:45.135897"
    },
    {
      "x": 4,
      "y": 6,
      "hit": false,
      "player_type": "player",
      "timestamp": "2025-05-24T22:51:45.267575"
    },
    {
      "x": 1,
      "y": 1,
      "hit": true,
      "player_type": "enemy",
      "timestamp": "2025-05-24T22:51:45.399925"
    },
    {
      "x": 5,
      "y": 9,
      "hit": false,
      "player_type": "enemy",
      "timestamp": "2025-05-24T22:51:45.582943"
    },
    {
      "x": 9,
      "y": 7,
      "hit": true,
      "player_type": "player",
      "timestamp": "2025-05-24T22:51:45.715539"
    },
    {
      "x": 9,
      "y": 8,
      "hit": false,
      "player_type": "player",
      "timestamp": "2025-05-24T22:51:45.894269"
    },
    {
      "x": 6,
      "y": 0,
      "hit": true,
      "player_type": "enemy",
      "timestamp": "2025-05-24T22:51:46.022196"
    },
    {
      "x": 6,
      "y": 1,
      "hit": false,
      "player_type": "enemy",
      "timestamp": "2025-05-24T22:51:46.200690"
    },
    {
      "x": 9,
      "y": 6,
      "hit": true,
      "player_type": "player",
      "timestamp": "2025-05-24T22:51:46.336471"
    },
    {
      "x": 6,
      "y": 9,
      "hit": false,
      "player_type": "player",
      "timestamp": "2025-05-24T22:51:46.516199"
    },
    {
      "x": 5,
      "y": 0,
      "hit": true,
      "player_type": "enemy",
      "timestamp": "2025-05-24T22:51:46.643884"
    },
    {
      "x": 5,
      "y": 1,
      "hit": false,
      "player_type": "enemy",
      "timestamp": "2025-05-24T22:51:46.823618"
    },
    {
      "x": 2,
      "y": 0,
      "hit": false,
      "player_type": "player",
      "timestamp": "2025-05-24T22:51:46.954468"
    },
    {
      "x": 4,
      "y": 0,
      "hit": false,
      "player_type": "enemy",
      "timestamp": "2025-05-24T22:51:47.088599"
    },
    {
      "x": 5,
      "y": 1,
      "hit": false,
      "player_type": "player",
      "timestamp": "2025-05-24T22:51:47.224212"
    },
    {
      "x": 7,
      "y": 0,
      "hit": true,
      "player_type": "enemy",
      "timestamp": "2025-05-24T22:51:47.352433"
    },
    {
      "x": 5,
      "y": 7,
      "hit": false,
      "player_type": "enemy",
      "timestamp": "2025-05-24T22:51:47.535260"
    },
    {
      "x": 1,
      "y": 3,
      "hit": true,
      "player_type": "player",
      "timestamp": "2025-05-24T22:51:47.665750"
    },
    {
      "x": 1,
      "y": 4,
      "hit": false,
      "player_type": "player",
      "timestamp": "2025-05-24T22:51:47.843858"
    },
    {
      "x": 4,
      "y": 8,
      "hit": false,
      "player_type": "enemy",
      "timestamp": "2025-05-24T22:51:47.971280"
    },
    {
      "x": 2,
      "y": 3,
      "hit": false,
      "player_type": "player",
      "timestamp": "2025-05-24T22:51:48.104306"
    },
    {
      "x": 2,
      "y": 3,
      "hit": true,
      "player_type": "enemy",
      "timestamp": "2025-05-24T22:51:48.237965"
    },
    {
      "x": 3,
      "y": 6,
      "hit": false,
      "player_type": "enemy",
      "timestamp": "2025-05-24T22:51:48.417916"
    },
    {
      "x": 1,
      "y": 2,
      "hit": true,
      "player_type": "player",
      "timestamp": "2025-05-24T22:51:48.553787"
    },
    {
      "x": 6,
      "y": 7,
      "hit": false,
      "player_type": "player",
      "timestamp": "2025-05-24T22:51:48.730865"
    },
    {
      "x": 5,
      "y": 8,
      "hit": false,
      "player_type": "enemy",
      "timestamp": "2025-05-24T22:51:48.860046"
    },
    {
      "x": 2,
      "y": 9,
      "hit": true,
      "player_type": "player",
      "timestamp": "2025-05-24T22:51:48.990432"
    },
    {
      "x": 3,
      "y": 9,
      "hit": true,
      "player_type": "player",
      "timestamp": "2025-05-24T22:51:49.164056"
    },
    {
      "x": 4,
      "y": 9,
      "hit": true,
      "player_type": "player",
      "timestamp": "2025-05-24T22:51:49.339956"
    },
    {
      "x": 5,
      "y": 9,
      "hit": false,
      "player_type": "player",
      "timestamp": "2025-05-24T22:51:49.513748"
    },
    {
      "x": 1,
      "y": 6,
      "hit": false,
      "player_type": "enemy",
      "timestamp": "2025-05-24T22:51:49.642842"
    },
    {
      "x": 2,
      "y": 8,
      "hit": false,
      "player_type": "player",
      "timestamp": "2025-05-24T22:51:49.775442"
    },
    {
      "x": 7,
      "y": 7,
      "hit": false,
      "player_type": "enemy",
      "timestamp": "2025-05-24T22:51:49.903717"
    },
    {
      "x": 1,
      "y": 9,
      "hit": true,
      "player_type": "player",
      "timestamp": "2025-05-24T22:51:50.051202"
    },
    {
      "x": 9,
      "y": 2,
      "hit": false,
      "player_type": "player",
      "timestamp": "2025-05-24T22:51:50.230550"
    },
    {
      "x": 0,
      "y": 8,
      "hit": false,
      "player_type": "enemy",
      "timestamp": "2025-05-24T22:51:50.366427"
    },
    {
      "x": 7,
      "y": 0,
      "hit": false,
      "player_type": "player",
      "timestamp": "2025-05-24T22:51:50.506079"
    },
    {
      "x": 1,
      "y": 9,
      "hit": false,
      "player_type": "enemy",
      "timestamp": "2025-05-24T22:51:50.637049"
    },
    {
      "x": 4,
      "y": 3,
      "hit": false,
      "player_type": "player",
      "timestamp": "2025-05-24T22:51:50.775174"
    },
    {
      "x": 9,
      "y": 9,
      "hit": false,
      "player_type": "enemy",
      "timestamp": "2025-05-24T22:51:50.903833"
    },
    {
      "x": 7,
      "y": 2,
      "hit": false,
      "player_type": "player",
      "timestamp": "2025-05-24T22:51:51.042385"
    },
    {
      "x": 8,
      "y": 6,
      "hit": true,
      "player_type": "enemy",
      "timestamp": "2025-05-24T22:51:51.169548"
    },
    {
      "x": 7,
      "y": 6,
      "hit": false,
      "player_type": "enemy",
      "timestamp": "2025-05-24T22:51:51.355210"
    },
    {
      "x": 6,
      "y": 4,
      "hit": false,
      "player_type": "player",
      "timestamp": "2025-05-24T22:51:51.488616"
    },
    {
      "x": 8,
      "y": 5,
      "hit": true,
      "player_type": "enemy",
      "timestamp": "2025-05-24T22:51:51.622699"
    },
    {
      "x": 2,
      "y": 8,
      "hit": false,
      "player_type": "enemy",
      "timestamp": "2025-05-24T22:51:51.802428"
    },
    {
      "x": 2,
      "y": 6,
      "hit": true,
      "player_type": "player",
      "timestamp": "2025-05-24T22:51:51.932353"
    },
    {
      "x": 2,
      "y": 7,
      "hit": true,
      "player_type": "player",
      "timestamp": "2025-05-24T22:51:52.110007"
    },
    {
      "x": 2,
      "y": 5,
      "hit": true,
      "player_type": "player",
      "timestamp": "2025-05-24T22:51:52.283332"
    },
    {
      "x": 9,
      "y": 0,
      "hit": false,
      "player_type": "player",
      "timestamp": "2025-05-24T22:51:52.456222"
    },
    {
      "x": 4,
      "y": 7,
      "hit": true,
      "player_type": "enemy",
      "timestamp": "2025-05-24T22:51:52.583687"
    },
    {
      "x": 0,
      "y": 9,
      "hit": false,
      "player_type": "enemy",
      "timestamp": "2025-05-24T22:51:52.767789"
    },
    {
      "x": 6,
      "y": 6,
      "hit": false,
      "player_type": "player",
      "timestamp": "2025-05-24T22:51:52.903257"
    },
    {
      "x": 1,
      "y": 7,
      "hit": false,
      "player_type": "enemy",
      "timestamp": "2025-05-24T22:51:53.037345"
    },
    {
      "x": 5,
      "y": 0,
      "hit": false,
      "player_type": "player",
      "timestamp": "2025-05-24T22:51:53.174863"
    },
    {
      "x": 9,
      "y": 8,
      "hit": false,
      "player_type": "enemy",
      "timestamp": "2025-05-24T22:51:53.302159"
    },
    {
      "x": 9,
      "y": 3,
      "hit": false,
      "player_type": "player",
      "timestamp": "2025-05-24T22:51:53.439392"
    },
    {
      "x": 4,
      "y": 4,
      "hit": true,
      "player_type": "enemy",
      "timestamp": "2025-05-24T22:51:53.569510"
    },
    {
      "x": 5,
      "y": 4,
      "hit": false,
      "player_type": "enemy",
      "timestamp": "2025-05-24T22:51:53.753296"
    },
    {
      "x": 6,
      "y": 5,
      "hit": true,
      "player_type": "player",
      "timestamp": "2025-05-24T22:51:53.884542"
    },
    {
      "x": 7,
      "y": 5,
      "hit": true,
      "player_type": "player",
      "timestamp": "2025-05-24T22:51:54.063790"
    },
    {
      "x": 9,
      "y": 1,
      "hit": false,
      "player_type": "player",
      "timestamp": "2025-05-24T22:51:54.236153"
    },
    {
      "x": 4,
      "y": 5,
      "hit": true,
      "player_type": "enemy",
      "timestamp": "2025-05-24T22:51:54.363954"
    },
    {
      "x": 3,
      "y": 5,
      "hit": false,
      "player_type": "enemy",
      "timestamp": "2025-05-24T22:51:54.541592"
    },
    {
      "x": 5,
      "y": 2,
      "hit": false,
      "player_type": "player",
      "timestamp": "2025-05-24T22:51:54.672724"
    },
    {
      "x": 5,
      "y": 5,
      "hit": false,
      "player_type": "enemy",
      "timestamp": "2025-05-24T22:51:54.802670"
    },
    {
      "x": 0,
      "y": 0,
      "hit": false,
      "player_type": "player",
      "timestamp": "2025-05-24T22:51:54.936999"
    },
    {
      "x": 4,
      "y": 3,
      "hit": true,
      "player_type": "enemy",
      "timestamp": "2025-05-24T22:51:55.069867"
    },
    {
      "x": 5,
      "y": 3,
      "hit": false,
      "player_type": "enemy",
      "timestamp": "2025-05-24T22:51:55.253103"
    },
    {
      "x": 7,
      "y": 1,
      "hit": false,
      "player_type": "player",
      "timestamp": "2025-05-24T22:51:55.386610"
    },
    {
      "x": 4,
      "y": 2,
      "hit": true,
      "player_type": "enemy",
      "timestamp": "2025-05-24T22:51:55.520293"
    },
    {
      "x": 7,
      "y": 2,
      "hit": false,
      "player_type": "enemy",
      "timestamp": "2025-05-24T22:51:55.703619"
    },
    {
      "x": 4,
      "y": 0,
      "hit": false,
      "player_type": "player",
      "timestamp": "2025-05-24T22:51:55.836327"
    },
    {
      "x": 6,
      "y": 4,
      "hit": false,
      "player_type": "enemy",
      "timestamp": "2025-05-24T22:51:55.970686"
    },
    {
      "x": 8,
      "y": 9,
      "hit": false,
      "player_type": "player",
      "timestamp": "2025-05-24T22:51:56.107757"
    },
    {
      "x": 6,
      "y": 2,
      "hit": true,
      "player_type": "enemy",
      "timestamp": "2025-05-24T22:51:56.236818"
    },
    {
      "x": 6,
      "y": 3,
      "hit": true,
      "player_type": "enemy",
      "timestamp": "2025-05-24T22:51:56.419471"
    },
    {
      "x": 2,
      "y": 9,
      "hit": false,
      "player_type": "enemy",
      "timestamp": "2025-05-24T22:51:56.596878"
    },
    {
      "x": 0,
      "y": 6,
      "hit": false,
      "player_type": "player",
      "timestamp": "2025-05-24T22:51:56.727347"
    },
    {
      "x": 6,
      "y": 6,
      "hit": false,
      "player_type": "enemy",
      "timestamp": "2025-05-24T22:51:56.855285"
    },
    {
      "x": 4,
      "y": 2,
      "hit": false,
      "player_type": "player",
      "timestamp": "2025-05-24T22:51:56.988917"
    },
    {
      "x": 6,
      "y": 5,
      "hit": false,
      "player_type": "enemy",
      "timestamp": "2025-05-24T22:51:57.120032"
    },
    {
      "x": 9,
      "y": 9,
      "hit": false,
      "player_type": "player",
      "timestamp": "2025-05-24T22:51:57.255479"
    },
    {
      "x": 0,
      "y": 3,
      "hit": false,
      "player_type": "enemy",
      "timestamp": "2025-05-24T22:51:57.387541"
    },
    {
      "x": 7,
      "y": 9,
      "hit": false,
      "player_type": "player",
      "timestamp": "2025-05-24T22:51:57.522267"
    },
    {
      "x": 9,
      "y": 2,
      "hit": false,
      "player_type": "enemy",
      "timestamp": "2025-05-24T22:51:57.657364"
    },
    {
      "x": 3,
      "y": 0,
      "hit": false,
      "player_type": "player",
      "timestamp": "2025-05-24T22:51:57.789749"
    },
    {
      "x": 2,
      "y": 6,
      "hit": false,
      "player_type": "enemy",
      "timestamp": "2025-05-24T22:51:57.919591"
    },
    {
      "x": 7,
      "y": 3,
      "hit": true,
      "player_type": "player",
      "timestamp": "2025-05-24T22:51:58.056903"
    },
    {
      "x": 8,
      "y": 3,
      "hit": true,
      "player_type": "player",
      "timestamp": "2025-05-24T22:51:58.232558"
    },
    {
      "x": 6,
      "y": 3,
      "hit": true,
      "player_type": "player",
      "timestamp": "2025-05-24T22:51:58.405474"
    },
    {
      "x": 6,
      "y": 0,
      "hit": false,
      "player_type": "player",
      "timestamp": "2025-05-24T22:51:58.578600"
    },
    {
      "x": 8,
      "y": 8,
      "hit": false,
      "player_type": "enemy",
      "timestamp": "2025-05-24T22:51:58.706976"
    },
    {
      "x": 8,
      "y": 0,
      "hit": true,
      "player_type": "player",
      "timestamp": "2025-05-24T22:51:58.837683"
    },
    {
      "x": 0,
      "y": 5,
      "hit": true,
      "player_type": "player",
      "timestamp": "2025-05-24T22:51:59.015094"
    },
    {
      "x": 1,
      "y": 0,
      "hit": false,
      "player_type": "player",
      "timestamp": "2025-05-24T22:51:59.187400"
    },
    {
      "x": 2,
      "y": 7,
      "hit": false,
      "player_type": "enemy",
      "timestamp": "2025-05-24T22:51:59.314380"
    },
    {
      "x": 6,
      "y": 8,
      "hit": false,
      "player_type": "player",
      "timestamp": "2025-05-24T22:51:59.450022"
    },
    {
      "x": 9,
      "y": 1,
      "hit": false,
      "player_type": "enemy",
      "timestamp": "2025-05-24T22:51:59.583801"
    },
    {
      "x": 3,
      "y": 2,
      "hit": false,
      "player_type": "player",
      "timestamp": "2025-05-24T22:51:59.718705"
    },
    {
      "x": 1,
      "y": 8,
      "hit": false,
      "player_type": "enemy",
      "timestamp": "2025-05-24T22:51:59.851227"
    },
    {
      "x": 0,
      "y": 7,
      "hit": true,
      "player_type": "player",
      "timestamp": "2025-05-24T22:51:59.989111"
    },
    {
      "x": 4,
      "y": 4,
      "hit": false,
      "player_type": "player",
      "timestamp": "2025-05-24T22:52:00.164830"
    },
    {
      "x": 0,
      "y": 7,
      "hit": false,
      "player_type": "enemy",
      "timestamp": "2025-05-24T22:52:00.293620"
    },
    {
      "x": 4,
      "y": 1,
      "hit": true,
      "player_type": "player",
      "timestamp": "2025-05-24T22:52:00.425224"
    }
  ],
  "initial_board_player": [
    [
      0,
      0,
      0,
      0,
      0,
      1,
      1,
      1,
      0,
      0
    ],
    [
      0,
      1,
      1,
      0,
      0,
      0,
      0,
      0,
      0,
      0
    ],
    [
      0,
      0,
      0,
      0,
      1,
      0,
      1,
      0,
      0,
      0
    ],
    [
      0,
      0,
      1,
      0,
      1,
      0,
      1,
      0,
      0,
      0
    ],
    [
      0,
      0,
      0,
      0,
      1,
      0,
      0,
      0,
      0,
      0
    ],
    [
      0,
      0,
      0,
      0,
      1,
      0,
      0,
      0,
      1,
      0
    ],
    [
      1,
      0,
      0,
      0,
      0,
      0,
      0,
      0,
      1,
      0
    ],
    [
      0,
      0,
      0,
      0,
      1,
      0,
      0,
      0,
      0,
      0
    ],
    [
      0,
      0,
      0,
      0,
      0,
      0,
      0,
      0,
      0,
      0
    ],
    [
      0,
      0,
      0,
      1,
      0,
      0,
      1,
      1,
      1,
      0
    ]
  ],
  "initial_board_ai": [
    [
      0,
      0,
      0,
      0,
      0,
      0,
      0,
      0,
      1,
      0
    ],
    [
      0,
      0,
      0,
      0,
      1,
      0,
      0,
      0,
      0,
      0
    ],
    [
      0,
      1,
      0,
      0,
      0,
      0,
      0,
      0,
      0,
      0
    ],
    [
      0,
      1,
      0,
      0,
      0,
      0,
      1,
      1,
      1,
      0
    ],
    [
      0,
      0,
      0,
      0,
      0,
      0,
      0,
      0,
      0,
      0
    ],
    [
      1,
      0,
      1,
      0,
      0,
      0,
      1,
      1,
      0,
      0
    ],
    [
      0,
      0,
      1,
      0,
      0,
      0,
      0,
      0,
      0,
      1
    ],
    [
      1,
      0,
      1,
      0,
      0,
      0,
      0,
      0,
      0,
      1
    ],
    [
      0,
      0,
      0,
      0,
      0,
      0,
      0,
      0,
      0,
      0
    ],
    [
      0,
      1,
      1,
      1,
      1,
      0,
      0,
      0,
      0,
      0
    ]
  ],
  "winner": "player",
  "total_moves": 106,
  "hits": 35,
  "misses": 71,
  "player_type": "ai",
  "player_ai_type": "algorithmic",
  "enemy_ai_type": "transformer",
  "player_board": null,
  "enemy_board": null,
  "start_time": null,
  "end_time": "2025-05-24T22:52:00.442395"
}