{
  "timestamp": "20250524_133323",
  "moves": [
    {
      "x": 0,
      "y": 1,
      "hit": true,
      "player_type": "player",
      "timestamp": "2025-05-24T13:33:28.337810"
    },
    {
      "x": 0,
      "y": 2,
      "hit": false,
      "player_type": "player",
      "timestamp": "2025-05-24T13:33:28.515877"
    },
    {
      "x": 1,
      "y": 6,
      "hit": false,
      "player_type": "enemy",
      "timestamp": "2025-05-24T13:33:28.640290"
    },
    {
      "x": 1,
      "y": 1,
      "hit": false,
      "player_type": "player",
      "timestamp": "2025-05-24T13:33:28.778945"
    },
    {
      "x": 3,
      "y": 1,
      "hit": true,
      "player_type": "enemy",
      "timestamp": "2025-05-24T13:33:28.908900"
    },
    {
      "x": 3,
      "y": 2,
      "hit": false,
      "player_type": "enemy",
      "timestamp": "2025-05-24T13:33:29.086917"
    },
    {
      "x": 0,
      "y": 0,
      "hit": true,
      "player_type": "player",
      "timestamp": "2025-05-24T13:33:29.218429"
    },
    {
      "x": 0,
      "y": 6,
      "hit": true,
      "player_type": "player",
      "timestamp": "2025-05-24T13:33:29.391443"
    },
    {
      "x": 0,
      "y": 7,
      "hit": true,
      "player_type": "player",
      "timestamp": "2025-05-24T13:33:29.564337"
    },
    {
      "x": 0,
      "y": 8,
      "hit": true,
      "player_type": "player",
      "timestamp": "2025-05-24T13:33:29.737551"
    },
    {
      "x": 3,
      "y": 9,
      "hit": false,
      "player_type": "player",
      "timestamp": "2025-05-24T13:33:29.911492"
    },
    {
      "x": 4,
      "y": 1,
      "hit": false,
      "player_type": "enemy",
      "timestamp": "2025-05-24T13:33:30.035636"
    },
    {
      "x": 9,
      "y": 6,
      "hit": false,
      "player_type": "player",
      "timestamp": "2025-05-24T13:33:30.166398"
    },
    {
      "x": 3,
      "y": 0,
      "hit": true,
      "player_type": "enemy",
      "timestamp": "2025-05-24T13:33:30.296237"
    },
    {
      "x": 6,
      "y": 3,
      "hit": false,
      "player_type": "enemy",
      "timestamp": "2025-05-24T13:33:30.476850"
    },
    {
      "x": 7,
      "y": 2,
      "hit": false,
      "player_type": "player",
      "timestamp": "2025-05-24T13:33:30.608938"
    },
    {
      "x": 5,
      "y": 7,
      "hit": false,
      "player_type": "enemy",
      "timestamp": "2025-05-24T13:33:30.738293"
    },
    {
      "x": 7,
      "y": 0,
      "hit": false,
      "player_type": "player",
      "timestamp": "2025-05-24T13:33:30.875360"
    },
    {
      "x": 1,
      "y": 9,
      "hit": true,
      "player_type": "enemy",
      "timestamp": "2025-05-24T13:33:31.004310"
    },
    {
      "x": 2,
      "y": 9,
      "hit": true,
      "player_type": "enemy",
      "timestamp": "2025-05-24T13:33:31.184590"
    },
    {
      "x": 0,
      "y": 0,
      "hit": false,
      "player_type": "enemy",
      "timestamp": "2025-05-24T13:33:31.359210"
    },
    {
      "x": 8,
      "y": 8,
      "hit": false,
      "player_type": "player",
      "timestamp": "2025-05-24T13:33:31.489436"
    },
    {
      "x": 4,
      "y": 5,
      "hit": false,
      "player_type": "enemy",
      "timestamp": "2025-05-24T13:33:31.612701"
    },
    {
      "x": 7,
      "y": 4,
      "hit": false,
      "player_type": "player",
      "timestamp": "2025-05-24T13:33:31.752561"
    },
    {
      "x": 9,
      "y": 0,
      "hit": true,
      "player_type": "enemy",
      "timestamp": "2025-05-24T13:33:31.876066"
    },
    {
      "x": 8,
      "y": 8,
      "hit": false,
      "player_type": "enemy",
      "timestamp": "2025-05-24T13:33:32.054163"
    },
    {
      "x": 6,
      "y": 7,
      "hit": false,
      "player_type": "player",
      "timestamp": "2025-05-24T13:33:32.185202"
    },
    {
      "x": 0,
      "y": 3,
      "hit": false,
      "player_type": "enemy",
      "timestamp": "2025-05-24T13:33:32.310530"
    },
    {
      "x": 5,
      "y": 2,
      "hit": false,
      "player_type": "player",
      "timestamp": "2025-05-24T13:33:32.450272"
    },
    {
      "x": 8,
      "y": 6,
      "hit": false,
      "player_type": "enemy",
      "timestamp": "2025-05-24T13:33:32.574540"
    },
    {
      "x": 5,
      "y": 9,
      "hit": true,
      "player_type": "player",
      "timestamp": "2025-05-24T13:33:32.706089"
    },
    {
      "x": 6,
      "y": 9,
      "hit": false,
      "player_type": "player",
      "timestamp": "2025-05-24T13:33:32.885785"
    },
    {
      "x": 9,
      "y": 4,
      "hit": false,
      "player_type": "enemy",
      "timestamp": "2025-05-24T13:33:33.010356"
    },
    {
      "x": 5,
      "y": 8,
      "hit": false,
      "player_type": "player",
      "timestamp": "2025-05-24T13:33:33.141128"
    },
    {
      "x": 6,
      "y": 9,
      "hit": false,
      "player_type": "enemy",
      "timestamp": "2025-05-24T13:33:33.271695"
    },
    {
      "x": 4,
      "y": 9,
      "hit": true,
      "player_type": "player",
      "timestamp": "2025-05-24T13:33:33.408961"
    },
    {
      "x": 9,
      "y": 0,
      "hit": false,
      "player_type": "player",
      "timestamp": "2025-05-24T13:33:33.586822"
    },
    {
      "x": 6,
      "y": 0,
      "hit": false,
      "player_type": "enemy",
      "timestamp": "2025-05-24T13:33:33.710979"
    },
    {
      "x": 3,
      "y": 4,
      "hit": false,
      "player_type": "player",
      "timestamp": "2025-05-24T13:33:33.848035"
    },
    {
      "x": 6,
      "y": 5,
      "hit": true,
      "player_type": "enemy",
      "timestamp": "2025-05-24T13:33:33.975093"
    },
    {
      "x": 2,
      "y": 4,
      "hit": false,
      "player_type": "enemy",
      "timestamp": "2025-05-24T13:33:34.148159"
    },
    {
      "x": 5,
      "y": 4,
      "hit": true,
      "player_type": "player",
      "timestamp": "2025-05-24T13:33:34.278796"
    },
    {
      "x": 9,
      "y": 2,
      "hit": false,
      "player_type": "player",
      "timestamp": "2025-05-24T13:33:34.458777"
    },
    {
      "x": 2,
      "y": 6,
      "hit": false,
      "player_type": "enemy",
      "timestamp": "2025-05-24T13:33:34.582928"
    },
    {
      "x": 3,
      "y": 0,
      "hit": false,
      "player_type": "player",
      "timestamp": "2025-05-24T13:33:34.715293"
    },
    {
      "x": 9,
      "y": 6,
      "hit": false,
      "player_type": "enemy",
      "timestamp": "2025-05-24T13:33:34.842181"
    },
    {
      "x": 9,
      "y": 4,
      "hit": false,
      "player_type": "player",
      "timestamp": "2025-05-24T13:33:34.979327"
    },
    {
      "x": 5,
      "y": 9,
      "hit": true,
      "player_type": "enemy",
      "timestamp": "2025-05-24T13:33:35.108741"
    },
    {
      "x": 5,
      "y": 8,
      "hit": false,
      "player_type": "enemy",
      "timestamp": "2025-05-24T13:33:35.290160"
    },
    {
      "x": 5,
      "y": 0,
      "hit": false,
      "player_type": "player",
      "timestamp": "2025-05-24T13:33:35.424727"
    },
    {
      "x": 4,
      "y": 9,
      "hit": true,
      "player_type": "enemy",
      "timestamp": "2025-05-24T13:33:35.554582"
    },
    {
      "x": 6,
      "y": 1,
      "hit": false,
      "player_type": "enemy",
      "timestamp": "2025-05-24T13:33:35.735516"
    },
    {
      "x": 3,
      "y": 1,
      "hit": false,
      "player_type": "player",
      "timestamp": "2025-05-24T13:33:35.865625"
    },
    {
      "x": 0,
      "y": 4,
      "hit": false,
      "player_type": "enemy",
      "timestamp": "2025-05-24T13:33:35.992317"
    },
    {
      "x": 3,
      "y": 6,
      "hit": false,
      "player_type": "player",
      "timestamp": "2025-05-24T13:33:36.128469"
    },
    {
      "x": 0,
      "y": 1,
      "hit": false,
      "player_type": "enemy",
      "timestamp": "2025-05-24T13:33:36.258408"
    },
    {
      "x": 9,
      "y": 8,
      "hit": false,
      "player_type": "player",
      "timestamp": "2025-05-24T13:33:36.405791"
    },
    {
      "x": 8,
      "y": 9,
      "hit": false,
      "player_type": "enemy",
      "timestamp": "2025-05-24T13:33:36.535951"
    },
    {
      "x": 8,
      "y": 6,
      "hit": false,
      "player_type": "player",
      "timestamp": "2025-05-24T13:33:36.667643"
    },
    {
      "x": 0,
      "y": 6,
      "hit": false,
      "player_type": "enemy",
      "timestamp": "2025-05-24T13:33:36.792765"
    },
    {
      "x": 5,
      "y": 1,
      "hit": false,
      "player_type": "player",
      "timestamp": "2025-05-24T13:33:36.929321"
    },
    {
      "x": 9,
      "y": 3,
      "hit": false,
      "player_type": "enemy",
      "timestamp": "2025-05-24T13:33:37.060798"
    },
    {
      "x": 2,
      "y": 4,
      "hit": false,
      "player_type": "player",
      "timestamp": "2025-05-24T13:33:37.191665"
    },
    {
      "x": 9,
      "y": 8,
      "hit": false,
      "player_type": "enemy",
      "timestamp": "2025-05-24T13:33:37.320808"
    },
    {
      "x": 0,
      "y": 4,
      "hit": false,
      "player_type": "player",
      "timestamp": "2025-05-24T13:33:37.456878"
    },
    {
      "x": 3,
      "y": 6,
      "hit": true,
      "player_type": "enemy",
      "timestamp": "2025-05-24T13:33:37.587570"
    },
    {
      "x": 3,
      "y": 7,
      "hit": false,
      "player_type": "enemy",
      "timestamp": "2025-05-24T13:33:37.768164"
    },
    {
      "x": 8,
      "y": 4,
      "hit": true,
      "player_type": "player",
      "timestamp": "2025-05-24T13:33:37.899706"
    },
    {
      "x": 8,
      "y": 5,
      "hit": true,
      "player_type": "player",
      "timestamp": "2025-05-24T13:33:38.073641"
    },
    {
      "x": 8,
      "y": 3,
      "hit": true,
      "player_type": "player",
      "timestamp": "2025-05-24T13:33:38.246437"
    },
    {
      "x": 8,
      "y": 1,
      "hit": false,
      "player_type": "player",
      "timestamp": "2025-05-24T13:33:38.420147"
    },
    {
      "x": 4,
      "y": 6,
      "hit": false,
      "player_type": "enemy",
      "timestamp": "2025-05-24T13:33:38.544506"
    },
    {
      "x": 3,
      "y": 2,
      "hit": false,
      "player_type": "player",
      "timestamp": "2025-05-24T13:33:38.679751"
    },
    {
      "x": 3,
      "y": 5,
      "hit": true,
      "player_type": "enemy",
      "timestamp": "2025-05-24T13:33:38.810525"
    },
    {
      "x": 3,
      "y": 4,
      "hit": true,
      "player_type": "enemy",
      "timestamp": "2025-05-24T13:33:38.989429"
    },
    {
      "x": 6,
      "y": 2,
      "hit": false,
      "player_type": "enemy",
      "timestamp": "2025-05-24T13:33:39.162308"
    },
    {
      "x": 9,
      "y": 9,
      "hit": false,
      "player_type": "player",
      "timestamp": "2025-05-24T13:33:39.292764"
    },
    {
      "x": 0,
      "y": 2,
      "hit": false,
      "player_type": "enemy",
      "timestamp": "2025-05-24T13:33:39.421315"
    },
    {
      "x": 8,
      "y": 9,
      "hit": false,
      "player_type": "player",
      "timestamp": "2025-05-24T13:33:39.559764"
    },
    {
      "x": 8,
      "y": 3,
      "hit": false,
      "player_type": "enemy",
      "timestamp": "2025-05-24T13:33:39.689754"
    },
    {
      "x": 4,
      "y": 6,
      "hit": false,
      "player_type": "player",
      "timestamp": "2025-05-24T13:33:39.828058"
    },
    {
      "x": 9,
      "y": 5,
      "hit": false,
      "player_type": "enemy",
      "timestamp": "2025-05-24T13:33:39.958125"
    },
    {
      "x": 0,
      "y": 3,
      "hit": true,
      "player_type": "player",
      "timestamp": "2025-05-24T13:33:40.096296"
    },
    {
      "x": 1,
      "y": 3,
      "hit": true,
      "player_type": "player",
      "timestamp": "2025-05-24T13:33:40.275902"
    },
    {
      "x": 6,
      "y": 0,
      "hit": false,
      "player_type": "player",
      "timestamp": "2025-05-24T13:33:40.449860"
    },
    {
      "x": 9,
      "y": 9,
      "hit": false,
      "player_type": "enemy",
      "timestamp": "2025-05-24T13:33:40.574797"
    },
    {
      "x": 8,
      "y": 0,
      "hit": false,
      "player_type": "player",
      "timestamp": "2025-05-24T13:33:40.711048"
    },
    {
      "x": 0,
      "y": 5,
      "hit": true,
      "player_type": "enemy",
      "timestamp": "2025-05-24T13:33:40.840962"
    },
    {
      "x": 9,
      "y": 2,
      "hit": false,
      "player_type": "enemy",
      "timestamp": "2025-05-24T13:33:41.020947"
    },
    {
      "x": 2,
      "y": 9,
      "hit": false,
      "player_type": "player",
      "timestamp": "2025-05-24T13:33:41.152045"
    },
    {
      "x": 7,
      "y": 9,
      "hit": false,
      "player_type": "enemy",
      "timestamp": "2025-05-24T13:33:41.276191"
    },
    {
      "x": 2,
      "y": 6,
      "hit": false,
      "player_type": "player",
      "timestamp": "2025-05-24T13:33:41.413708"
    },
    {
      "x": 7,
      "y": 0,
      "hit": true,
      "player_type": "enemy",
      "timestamp": "2025-05-24T13:33:41.542639"
    },
    {
      "x": 7,
      "y": 1,
      "hit": true,
      "player_type": "enemy",
      "timestamp": "2025-05-24T13:33:41.723136"
    },
    {
      "x": 7,
      "y": 2,
      "hit": true,
      "player_type": "enemy",
      "timestamp": "2025-05-24T13:33:41.896268"
    },
    {
      "x": 7,
      "y": 3,
      "hit": true,
      "player_type": "enemy",
      "timestamp": "2025-05-24T13:33:42.069189"
    },
    {
      "x": 5,
      "y": 0,
      "hit": false,
      "player_type": "enemy",
      "timestamp": "2025-05-24T13:33:42.242223"
    },
    {
      "x": 9,
      "y": 7,
      "hit": false,
      "player_type": "player",
      "timestamp": "2025-05-24T13:33:42.373182"
    },
    {
      "x": 0,
      "y": 7,
      "hit": false,
      "player_type": "enemy",
      "timestamp": "2025-05-24T13:33:42.504036"
    },
    {
      "x": 7,
      "y": 9,
      "hit": true,
      "player_type": "player",
      "timestamp": "2025-05-24T13:33:42.634979"
    },
    {
      "x": 2,
      "y": 0,
      "hit": false,
      "player_type": "player",
      "timestamp": "2025-05-24T13:33:42.808769"
    },
    {
      "x": 1,
      "y": 0,
      "hit": false,
      "player_type": "enemy",
      "timestamp": "2025-05-24T13:33:42.933631"
    },
    {
      "x": 4,
      "y": 0,
      "hit": false,
      "player_type": "player",
      "timestamp": "2025-05-24T13:33:43.064952"
    },
    {
      "x": 9,
      "y": 7,
      "hit": false,
      "player_type": "enemy",
      "timestamp": "2025-05-24T13:33:43.191386"
    },
    {
      "x": 4,
      "y": 7,
      "hit": true,
      "player_type": "player",
      "timestamp": "2025-05-24T13:33:43.329625"
    },
    {
      "x": 5,
      "y": 7,
      "hit": true,
      "player_type": "player",
      "timestamp": "2025-05-24T13:33:43.508551"
    },
    {
      "x": 3,
      "y": 7,
      "hit": true,
      "player_type": "player",
      "timestamp": "2025-05-24T13:33:43.682258"
    },
    {
      "x": 7,
      "y": 7,
      "hit": false,
      "player_type": "player",
      "timestamp": "2025-05-24T13:33:43.855836"
    },
    {
      "x": 7,
      "y": 8,
      "hit": false,
      "player_type": "enemy",
      "timestamp": "2025-05-24T13:33:43.980604"
    },
    {
      "x": 2,
      "y": 7,
      "hit": true,
      "player_type": "player",
      "timestamp": "2025-05-24T13:33:44.117245"
    },
    {
      "x": 9,
      "y": 1,
      "hit": true,
      "player_type": "player",
      "timestamp": "2025-05-24T13:33:44.291618"
    },
    {
      "x": 6,
      "y": 1,
      "hit": false,
      "player_type": "player",
      "timestamp": "2025-05-24T13:33:44.464652"
    },
    {
      "x": 1,
      "y": 2,
      "hit": true,
      "player_type": "enemy",
      "timestamp": "2025-05-24T13:33:44.589982"
    },
    {
      "x": 1,
      "y": 3,
      "hit": true,
      "player_type": "enemy",
      "timestamp": "2025-05-24T13:33:44.770167"
    },
    {
      "x": 1,
      "y": 1,
      "hit": true,
      "player_type": "enemy",
      "timestamp": "2025-05-24T13:33:44.943452"
    },
    {
      "x": 7,
      "y": 7,
      "hit": false,
      "player_type": "enemy",
      "timestamp": "2025-05-24T13:33:45.116535"
    },
    {
      "x": 4,
      "y": 2,
      "hit": false,
      "player_type": "player",
      "timestamp": "2025-05-24T13:33:45.245774"
    },
    {
      "x": 5,
      "y": 2,
      "hit": false,
      "player_type": "enemy",
      "timestamp": "2025-05-24T13:33:45.375506"
    },
    {
      "x": 6,
      "y": 2,
      "hit": false,
      "player_type": "player",
      "timestamp": "2025-05-24T13:33:45.511051"
    },
    {
      "x": 1,
      "y": 7,
      "hit": false,
      "player_type": "enemy",
      "timestamp": "2025-05-24T13:33:45.642591"
    },
    {
      "x": 2,
      "y": 5,
      "hit": true,
      "player_type": "player",
      "timestamp": "2025-05-24T13:33:45.778192"
    }
  ],
  "initial_board_player": [
    [
      0,
      0,
      0,
      1,
      0,
      0,
      0,
      1,
      0,
      1
    ],
    [
      0,
      1,
      0,
      1,
      0,
      0,
      0,
      1,
      0,
      0
    ],
    [
      0,
      1,
      0,
      0,
      0,
      0,
      0,
      1,
      0,
      0
    ],
    [
      0,
      1,
      0,
      0,
      0,
      0,
      0,
      1,
      0,
      0
    ],
    [
      0,
      0,
      0,
      1,
      0,
      0,
      0,
      0,
      0,
      0
    ],
    [
      1,
      0,
      0,
      1,
      0,
      0,
      1,
      0,
      1,
      0
    ],
    [
      0,
      0,
      0,
      1,
      0,
      0,
      0,
      0,
      0,
      0
    ],
    [
      0,
      0,
      0,
      0,
      0,
      0,
      0,
      0,
      0,
      0
    ],
    [
      0,
      0,
      0,
      0,
      0,
      0,
      0,
      0,
      0,
      0
    ],
    [
      0,
      1,
      1,
      0,
      1,
      1,
      0,
      0,
      0,
      0
    ]
  ],
  "initial_board_ai": [
    [
      1,
      0,
      0,
      0,
      0,
      0,
      0,
      0,
      0,
      0
    ],
    [
      1,
      0,
      0,
      0,
      0,
      0,
      0,
      0,
      0,
      1
    ],
    [
      0,
      0,
      0,
      0,
      0,
      0,
      0,
      0,
      0,
      0
    ],
    [
      1,
      1,
      0,
      0,
      0,
      0,
      0,
      0,
      1,
      0
    ],
    [
      0,
      0,
      0,
      0,
      0,
      1,
      0,
      0,
      1,
      0
    ],
    [
      0,
      0,
      1,
      0,
      0,
      0,
      0,
      0,
      1,
      0
    ],
    [
      1,
      0,
      0,
      0,
      0,
      0,
      0,
      0,
      0,
      0
    ],
    [
      1,
      0,
      1,
      1,
      1,
      1,
      0,
      0,
      0,
      0
    ],
    [
      1,
      0,
      0,
      0,
      0,
      0,
      0,
      0,
      0,
      0
    ],
    [
      0,
      0,
      0,
      0,
      1,
      1,
      0,
      1,
      0,
      0
    ]
  ],
  "winner": "player",
  "total_moves": 121,
  "hits": 39,
  "misses": 82,
  "player_type": "ai",
  "player_ai_type": "algorithmic",
  "enemy_ai_type": "transformer",
  "player_board": null,
  "enemy_board": null,
  "start_time": null,
  "end_time": "2025-05-24T13:33:45.802011"
}